tefu/__init__.py
tefu/loader.py
tefu/main.py
tefu/runner.py
tefu/status.py
tefu/variable.py
tefu-0.1.0.dist-info/METADATA
tefu-0.1.0.dist-info/WHEEL
tefu-0.1.0.dist-info/entry_points.txt
tefu-0.1.0.dist-info/RECORD
