Metadata-Version: 2.1
Name: tefu
Version: 0.1.0
Summary: Add your description here
Author-email: Comamoca <comamoca.dev@gmail.com>
Requires-Python: >=3.8
Requires-Dist: click>=8.1.7
Requires-Dist: tabulate>=0.9.0
Requires-Dist: toolz>=0.12.0
